remarkbox/__init__.py
remarkbox/routes.py
remarkbox/lib/__init__.py
remarkbox/lib/mail.py
remarkbox/lib/mail_messages.py
remarkbox/lib/notify.py
remarkbox/lib/render.py
remarkbox/lib/sanitize_html.py
remarkbox/lib/svgtar/__init__.py
remarkbox/lib/svgtar/svg.py
remarkbox/models/__init__.py
remarkbox/models/event.py
remarkbox/models/meta.py
remarkbox/models/namespace.py
remarkbox/models/namespace_request.py
remarkbox/models/namespace_user.py
remarkbox/models/node.py
remarkbox/models/node_cache.py
remarkbox/models/notification.py
remarkbox/models/oauth.py
remarkbox/models/pay_what_you_can.py
remarkbox/models/payment.py
remarkbox/models/uri.py
remarkbox/models/user.py
remarkbox/models/vote.py
remarkbox/models/watcher.py
remarkbox/scripts/__init__.py
remarkbox/scripts/delete_disabled_nodes.py
remarkbox/scripts/init_db.py
remarkbox/scripts/invalidate_node_cache.py
remarkbox/scripts/json_import.py
remarkbox/scripts/merge_dupes.py
remarkbox/scripts/modify_namespace.py
remarkbox/scripts/modify_node.py
remarkbox/scripts/modify_uris.py
remarkbox/scripts/modify_user.py
remarkbox/scripts/recompute_node_depths.py
remarkbox/scripts/safe_approve_all_nodes.py
remarkbox/scripts/send_node_digest_notifications.py
remarkbox/scripts/alembic/env.py
remarkbox/scripts/alembic/script.py.mako
remarkbox/scripts/alembic/versions/00211ed642cc_add_ip_address_column_to_rb_node.py
remarkbox/scripts/alembic/versions/0208c10ea67f_create_new_node_cache_table.py
remarkbox/scripts/alembic/versions/04e52337756e_autogenerated_indicies.py
remarkbox/scripts/alembic/versions/051f8b810f26_namespace_ignore_query_string.py
remarkbox/scripts/alembic/versions/1040ee4836af_namespace_description.py
remarkbox/scripts/alembic/versions/108519de76ac_add_allow_anonymous_column_to_namespace.py
remarkbox/scripts/alembic/versions/14a6a35940c7_new_field_for_namespace_request_cache.py
remarkbox/scripts/alembic/versions/184a349cd589_uri_accessed_timestamp.py
remarkbox-1.0.5.dist-info/METADATA
remarkbox-1.0.5.dist-info/WHEEL
remarkbox-1.0.5.dist-info/entry_points.txt
remarkbox-1.0.5.dist-info/top_level.txt
remarkbox-1.0.5.dist-info/RECORD
