Metadata-Version: 2.1
Name: remarkbox
Version: 1.0.5
Summary: remarkbox
Home-page: https://russell.ballestrini.net
Author: Russell Ballestrini
Author-email: russell@ballestrini.net
Keywords: remarkbox question answer forum embed comments reviews
Classifier: Programming Language :: Python :: 3
Classifier: Programming Language :: Python :: 3.6
Classifier: Programming Language :: Python :: 3.7
Classifier: Programming Language :: Python :: 3.8
Classifier: Programming Language :: Python :: 3.9
Classifier: Programming Language :: Python :: 3.10
Classifier: Programming Language :: Python :: 3.11
Classifier: Programming Language :: Python :: 3.12
Classifier: Programming Language :: Python :: 3.13
Classifier: Programming Language :: Python :: 3.14
Classifier: Programming Language :: Python :: 3.15
Classifier: Programming Language :: Python
Classifier: Framework :: Pyramid
Classifier: Topic :: Internet :: WWW/HTTP
Classifier: Topic :: Internet :: WWW/HTTP :: WSGI :: Application
Requires-Dist: BeautifulSoup4
Requires-Dist: SQLAlchemy
Requires-Dist: SQLAlchemy-Utils
Requires-Dist: ago
Requires-Dist: alembic
Requires-Dist: bcrypt
Requires-Dist: bleach-allowlist
Requires-Dist: bleach >=2.1.4
Requires-Dist: dkimpy
Requires-Dist: html5lib
Requires-Dist: jinja2
Requires-Dist: markdown
Requires-Dist: miniuri
Requires-Dist: plaster-pastedeploy
Requires-Dist: psycopg2-binary
Requires-Dist: pygments
Requires-Dist: pyramid
Requires-Dist: pyramid-debugtoolbar
Requires-Dist: pyramid-jinja2
Requires-Dist: pyramid-retry
Requires-Dist: pyramid-tm
Requires-Dist: python-markdown-math
Requires-Dist: python-slugify
Requires-Dist: requests[security]
Requires-Dist: six
Requires-Dist: slacker
Requires-Dist: stripe
Requires-Dist: transaction
Requires-Dist: zope.sqlalchemy
Provides-Extra: dev
Requires-Dist: bpython ; extra == 'dev'
Requires-Dist: pyramid-bpython ; extra == 'dev'
Requires-Dist: waitress ; extra == 'dev'
Provides-Extra: prod
Requires-Dist: psycopg2 ; extra == 'prod'
Requires-Dist: uwsgi ; extra == 'prod'
Provides-Extra: test
Requires-Dist: fakeredis ; extra == 'test'
Requires-Dist: mock ; extra == 'test'
Requires-Dist: nose ; extra == 'test'
Requires-Dist: pytest ; extra == 'test'
Requires-Dist: webtest ; extra == 'test'
